multi_crypt/__init__.py
multi_crypt/crypt.py
multi_crypt/errors.py
multi_crypt/multi_crypt.py
multi_crypt/utils.py
multi_crypt/_libboqs/__init__.py
multi_crypt/_libboqs/pq_base.py
multi_crypt/algorithms/__init__.py
multi_crypt/algorithms/ec_secp256k1.py
multi_crypt/algorithms/pq_ml_kem_1024_ml_dsa_87.py
multi_crypt/algorithms/pq_ml_kem_768_ml_dsa_65.py
multi_crypt-0.1.3.dist-info/licenses/LICENSE
multi_crypt-0.1.3.dist-info/licenses/LICENSE-CC0
multi_crypt-0.1.3.dist-info/METADATA
multi_crypt-0.1.3.dist-info/WHEEL
multi_crypt-0.1.3.dist-info/top_level.txt
multi_crypt-0.1.3.dist-info/RECORD
