Metadata-Version: 2.4
Name: multi_crypt
Version: 0.1.3
Summary: A single unified interface for working with alternative cryptographic algorithms.
Author: emendir
License-Expression: MIT-0 OR CC0-1.0
License-File: LICENSE
License-File: LICENSE-CC0
Requires-Dist: pycryptodome
Requires-Dist: eciespy
Requires-Dist: liboqs-python
Dynamic: license-file
